pyxylookup/__init__.py
tests/__init__.py
tests/test_lookup.py
pyxylookup-0.2.1.dist-info/LICENSE
pyxylookup-0.2.1.dist-info/METADATA
pyxylookup-0.2.1.dist-info/WHEEL
pyxylookup-0.2.1.dist-info/top_level.txt
pyxylookup-0.2.1.dist-info/RECORD
