Metadata-Version: 2.1
Name: pyxylookup
Version: 0.2.1
Summary: Python client for the OBIS xylookup API
Home-page: http://github.com/iobis/pyxylookup
Author: Samuel Bosch
Author-email: mail@samuelbosch.com
License: MIT
Classifier: Intended Audience :: Science/Research
Classifier: Topic :: Scientific/Engineering :: Bio-Informatics
Classifier: Natural Language :: English
Classifier: License :: OSI Approved :: MIT License
Classifier: Programming Language :: Python
Classifier: Programming Language :: Python :: 2.7
Classifier: Programming Language :: Python :: 3
License-File: LICENSE
Requires-Dist: requests (>2.7)
Requires-Dist: msgpack (>=0.5.6)
Requires-Dist: numpy (>=1.14.0)
